nonebot_plugin_open_file/__init__.py
nonebot_plugin_open_file/config.py
nonebot_plugin_open_file-1.0.0.dist-info/METADATA
nonebot_plugin_open_file-1.0.0.dist-info/WHEEL
nonebot_plugin_open_file-1.0.0.dist-info/RECORD
