Metadata-Version: 2.4
Name: nonebot-plugin-open-file
Version: 1.0.0
Summary: 通过检测特定私聊关键词来打开对应文件的 NoneBot2 插件
License: MIT
Keywords: nonebot,nonebot2,plugin,file,opener,remote
Author: 星淆_xenith
Requires-Python: >=3.9,<4.0
Classifier: License :: OSI Approved :: MIT License
Classifier: Programming Language :: Python :: 3
Classifier: Programming Language :: Python :: 3.9
Classifier: Programming Language :: Python :: 3.10
Classifier: Programming Language :: Python :: 3.11
Classifier: Programming Language :: Python :: 3.12
Classifier: Programming Language :: Python :: 3.13
Classifier: Programming Language :: Python :: 3.14
Provides-Extra: dev
Requires-Dist: black ; extra == "dev"
Requires-Dist: flake8 ; extra == "dev"
Requires-Dist: isort ; extra == "dev"
Requires-Dist: nonebot-adapter-onebot (>=2.0.0)
Requires-Dist: nonebot2 (>=2.0.0)
Requires-Dist: pydantic (>=1.10.0,<3.0.0)
Requires-Dist: pytest ; extra == "dev"
Requires-Dist: pytest-asyncio ; extra == "dev"
Project-URL: Documentation, https://github.com/Xenith-Ethereon/nonebot-plugin-open-file.git
Project-URL: Homepage, https://github.com/Xenith-Ethereon/nonebot-plugin-open-file.git
Project-URL: Repository, https://github.com/Xenith-Ethereon/nonebot-plugin-open-file.git
